sopel_modules.youtube-0.5.2-py3.12-nspkg.pth
sopel_modules/youtube/__init__.py
sopel_modules/youtube/youtube.py
tests/__init__.py
tests/test_youtube.py
sopel_modules.youtube-0.5.2.dist-info/COPYING
sopel_modules.youtube-0.5.2.dist-info/METADATA
sopel_modules.youtube-0.5.2.dist-info/WHEEL
sopel_modules.youtube-0.5.2.dist-info/namespace_packages.txt
sopel_modules.youtube-0.5.2.dist-info/top_level.txt
sopel_modules.youtube-0.5.2.dist-info/RECORD
