Metadata-Version: 2.1
Name: sopel_modules.youtube
Version: 0.5.2
Summary: YouTube plugin for Sopel
Home-page: https://github.com/sopel-irc/sopel-youtube
Author: dgw
Author-email: dgw@technobabbl.es
License: Eiffel Forum License, version 2
License-File: COPYING
Requires-Dist: sopel <8,>=7.1
Requires-Dist: setuptools
Requires-Dist: google-api-python-client <1.8,>=1.5.5 ; python_version < "3.6"
Requires-Dist: google-api-python-client <3,>=1.5.5 ; python_version >= "3.6"
